build/lib/build/lib/build/lib/build/lib/build/lib/build/lib/build/lib/build/lib/build/lib/build/lib/pytopocomplexity/__init__.py
build/lib/build/lib/build/lib/build/lib/build/lib/build/lib/build/lib/build/lib/build/lib/build/lib/pytopocomplexity/pycwtmexhat.py
build/lib/build/lib/build/lib/build/lib/build/lib/build/lib/build/lib/build/lib/build/lib/build/lib/pytopocomplexity/pyfracd.py
build/lib/build/lib/build/lib/build/lib/build/lib/build/lib/build/lib/build/lib/build/lib/build/lib/pytopocomplexity/pyrugosity.py
build/lib/build/lib/build/lib/build/lib/build/lib/build/lib/build/lib/build/lib/build/lib/build/lib/pytopocomplexity/pytpi.py
build/lib/build/lib/build/lib/build/lib/build/lib/build/lib/build/lib/build/lib/build/lib/pytopocomplexity/__init__.py
build/lib/build/lib/build/lib/build/lib/build/lib/build/lib/build/lib/build/lib/build/lib/pytopocomplexity/pycwtmexhat.py
build/lib/build/lib/build/lib/build/lib/build/lib/build/lib/build/lib/build/lib/build/lib/pytopocomplexity/pyfracd.py
build/lib/build/lib/build/lib/build/lib/build/lib/build/lib/build/lib/build/lib/build/lib/pytopocomplexity/pyrugosity.py
build/lib/build/lib/build/lib/build/lib/build/lib/build/lib/build/lib/build/lib/build/lib/pytopocomplexity/pytpi.py
build/lib/build/lib/build/lib/build/lib/build/lib/build/lib/build/lib/build/lib/pytopocomplexity/__init__.py
build/lib/build/lib/build/lib/build/lib/build/lib/build/lib/build/lib/build/lib/pytopocomplexity/pycwtmexhat.py
build/lib/build/lib/build/lib/build/lib/build/lib/build/lib/build/lib/build/lib/pytopocomplexity/pyfracd.py
build/lib/build/lib/build/lib/build/lib/build/lib/build/lib/build/lib/build/lib/pytopocomplexity/pyrugosity.py
build/lib/build/lib/build/lib/build/lib/build/lib/build/lib/build/lib/build/lib/pytopocomplexity/pytpi.py
build/lib/build/lib/build/lib/build/lib/build/lib/build/lib/build/lib/pytopocomplexity/__init__.py
build/lib/build/lib/build/lib/build/lib/build/lib/build/lib/build/lib/pytopocomplexity/pycwtmexhat.py
pytopocomplexity-1.1.2.dist-info/licenses/LICENSE
pytopocomplexity-1.1.2.dist-info/METADATA
pytopocomplexity-1.1.2.dist-info/WHEEL
pytopocomplexity-1.1.2.dist-info/top_level.txt
pytopocomplexity-1.1.2.dist-info/RECORD
