Metadata-Version: 2.4
Name: pytopocomplexity
Version: 1.1.2
Summary: A package for multiscale topographic complexity analysis
Home-page: https://github.com/GeoLarryLai/pyTopoComplexity
Author: Larry Syu-Heng Lai
Author-email: Larry Syu-Heng Lai <larrysyuhenglai@gmail.com>
License:                     GNU AFFERO GENERAL PUBLIC LICENSE
Project-URL: repository, https://github.com/GeoLarryLai/pyTopoComplexity.git
Classifier: Programming Language :: Python :: 3
Classifier: License :: OSI Approved :: GNU Affero General Public License v3
Classifier: Operating System :: OS Independent
Requires-Python: >=3.10
License-File: LICENSE
Requires-Dist: numpy>=1.20
Requires-Dist: scipy>=1.5
Requires-Dist: rasterio>=1.2
Requires-Dist: dask>=2021.0
Requires-Dist: matplotlib>=3.3
Requires-Dist: tqdm>=4.0
Requires-Dist: numba>=0.50
Requires-Dist: statsmodels>=0.12
Requires-Dist: gdal>=3.0
Requires-Dist: ipython>=7.0
Requires-Dist: imageio>=2.9
Dynamic: author
Dynamic: home-page
Dynamic: license-file
Dynamic: requires-python
